{"text": " I am ready. I am ready. Are you ready? Is that wrong? Can you... can you repeat that one more time? Because in the middle, you're not there. I'm not catching... I'm not picking up some words. Can you repeat the question? Yeah. Yep. One and a half. I didn't think it was, but apparently it is. I am ready. I am ready. Are you ready? Is that wrong? Can you... can you repeat that one more time? Because in the middle, you're not there. I'm not catching... I'm not picking up some words. Can you repeat the question? Yeah. One and a half. I didn't think it was, but apparently it is.", "segments": [{"id": 0, "seek": 0, "start": 0.0, "end": 2.0, "text": " I am ready. I am ready.", "tokens": [286, 669, 1919, 13, 286, 669, 1919, 13], "temperature": 0.0, "avg_logprob": -0.279709056932099, "compression_ratio": 1.5449735449735449, "no_speech_prob": 0.16010499000549316}, {"id": 0, "seek": 0, "start": 2.0, "end": 4.0, "text": " Are you ready? Is that wrong?", "tokens": [2014, 291, 1919, 30, 1119, 300, 2085, 30], "temperature": 0.0, "avg_logprob": -0.279709056932099, "compression_ratio": 1.5449735449735449, "no_speech_prob": 0.16010499000549316}, {"id": 0, "seek": 0, "start": 4.0, "end": 7.0, "text": " Can you... can you repeat that one more time?", "tokens": [1664, 291, 485, 393, 291, 7149, 300, 472, 544, 565, 30], "temperature": 0.0, "avg_logprob": -0.279709056932099, "compression_ratio": 1.5449735449735449, "no_speech_prob": 0.16010499000549316}, {"id": 0, "seek": 0, "start": 7.0, "end": 10.0, "text": " Because in the middle, you're not there.", "tokens": [1436, 294, 264, 2808, 11, 291, 434, 406, 456, 13], "temperature": 0.0, "avg_logprob": -0.279709056932099, "compression_ratio": 1.5449735449735449, "no_speech_prob": 0.16010499000549316}, {"id": 0, "seek": 0, "start": 10.0, "end": 13.0, "text": " I'm not catching... I'm not picking up some words.", "tokens": [286, 478, 406, 16124, 485, 286, 478, 406, 8867, 493, 512, 2283, 13], "temperature": 0.0, "avg_logprob": -0.279709056932099, "compression_ratio": 1.5449735449735449, "no_speech_prob": 0.16010499000549316}, {"id": 0, "seek": 0, "start": 13.0, "end": 14.0, "text": " Can you repeat the question?", "tokens": [1664, 291, 7149, 264, 1168, 30], "temperature": 0.0, "avg_logprob": -0.279709056932099, "compression_ratio": 1.5449735449735449, "no_speech_prob": 0.16010499000549316}, {"id": 0, "seek": 0, "start": 14.0, "end": 15.0, "text": " Yeah.", "tokens": [865, 13], "temperature": 0.0, "avg_logprob": -0.279709056932099, "compression_ratio": 1.5449735449735449, "no_speech_prob": 0.16010499000549316}, {"id": 0, "seek": 0, "start": 15.0, "end": 15.0, "text": "", "tokens": [], "temperature": 0.0, "avg_logprob": -0.279709056932099, "compression_ratio": 1.5449735449735449, "no_speech_prob": 0.16010499000549316, "words": []}, {"id": 0, "seek": 0, "start": 15.0, "end": 16.0, "text": " One and a half.", "tokens": [1485, 293, 257, 1922, 13], "temperature": 0.0, "avg_logprob": -0.279709056932099, "compression_ratio": 1.5449735449735449, "no_speech_prob": 0.16010499000549316}, {"id": 0, "seek": 0, "start": 16.0, "end": 19.0, "text": " I didn't think it was, but apparently it is.", "tokens": [286, 994, 380, 519, 309, 390, 11, 457, 7970, 309, 307, 13], "temperature": 0.0, "avg_logprob": -0.279709056932099, "compression_ratio": 1.5449735449735449, "no_speech_prob": 0.16010499000549316}], "language": "en"}