{"text": " I do. Yes. Okay. Alright. Yeah. 310, 28. Yes. 340, euro. I do. Yes. Okay. Alright. Yeah. 310, 28. Yes. 340, euro.", "segments": [{"id": 0, "seek": 0, "start": 0.0, "end": 2.0, "text": " I do. Yes.", "tokens": [286, 360, 13, 1079, 13], "temperature": 0.0, "avg_logprob": -0.5563866464715255, "compression_ratio": 1.018181818181818, "no_speech_prob": 0.3078989088535309}, {"id": 0, "seek": 0, "start": 2.0, "end": 3.0, "text": " Okay.", "tokens": [1033, 13], "temperature": 0.0, "avg_logprob": -0.5563866464715255, "compression_ratio": 1.018181818181818, "no_speech_prob": 0.3078989088535309}, {"id": 0, "seek": 0, "start": 3.0, "end": 4.0, "text": " Alright.", "tokens": [2798, 13], "temperature": 0.0, "avg_logprob": -0.5563866464715255, "compression_ratio": 1.018181818181818, "no_speech_prob": 0.3078989088535309}, {"id": 0, "seek": 0, "start": 4.0, "end": 5.0, "text": " Yeah.", "tokens": [865, 13], "temperature": 0.0, "avg_logprob": -0.5563866464715255, "compression_ratio": 1.018181818181818, "no_speech_prob": 0.3078989088535309}, {"id": 0, "seek": 0, "start": 5.0, "end": 8.0, "text": " 310, 28.", "tokens": [805, 3279, 11, 7562, 13], "temperature": 0.0, "avg_logprob": -0.5563866464715255, "compression_ratio": 1.018181818181818, "no_speech_prob": 0.3078989088535309}, {"id": 0, "seek": 0, "start": 8.0, "end": 9.0, "text": " Yes.", "tokens": [1079, 13], "temperature": 0.0, "avg_logprob": -0.5563866464715255, "compression_ratio": 1.018181818181818, "no_speech_prob": 0.3078989088535309}, {"id": 0, "seek": 0, "start": 9.0, "end": 11.0, "text": " 340, euro.", "tokens": [805, 5254, 11, 14206, 13], "temperature": 0.0, "avg_logprob": -0.5563866464715255, "compression_ratio": 1.018181818181818, "no_speech_prob": 0.3078989088535309}], "language": "en"}