{"text": " Can you repeat that question? Can you repeat the question? It's easy. No, thank you. No, thank you. Can you repeat that question? Can you repeat the question? It's easy. No, thank you. No, thank you.", "segments": [{"id": 0, "seek": 0, "start": 0.0, "end": 1.12, "text": " Can you repeat that question?", "tokens": [1664, 291, 7149, 300, 1168, 30], "temperature": 0.0, "avg_logprob": -0.6563866074020798, "compression_ratio": 1.546875, "no_speech_prob": 0.21817491948604584}, {"id": 0, "seek": 0, "start": 1.12, "end": 2.52, "text": " Can you repeat the question?", "tokens": [1664, 291, 7149, 264, 1168, 30], "temperature": 0.0, "avg_logprob": -0.6563866074020798, "compression_ratio": 1.546875, "no_speech_prob": 0.21817491948604584}, {"id": 0, "seek": 0, "start": 2.52, "end": 3.2, "text": " It's easy.", "tokens": [467, 311, 1858, 13], "temperature": 0.0, "avg_logprob": -0.6563866074020798, "compression_ratio": 1.546875, "no_speech_prob": 0.21817491948604584}, {"id": 0, "seek": 0, "start": 3.2, "end": 3.72, "text": " No, thank you.", "tokens": [883, 11, 1309, 291, 13], "temperature": 0.0, "avg_logprob": -0.6563866074020798, "compression_ratio": 1.546875, "no_speech_prob": 0.21817491948604584}, {"id": 0, "seek": 0, "start": 3.72, "end": 4.5600000000000005, "text": " No, thank you.", "tokens": [883, 11, 1309, 291, 13], "temperature": 0.0, "avg_logprob": -0.6563866074020798, "compression_ratio": 1.546875, "no_speech_prob": 0.21817491948604584}], "language": "en"}